leanmq/__init__.py
leanmq/core.py
leanmq/exceptions.py
leanmq/message.py
leanmq/queue.py
leanmq/transaction.py
leanmq/webhook.py
leanmq-0.2.0.dist-info/LICENSE
leanmq-0.2.0.dist-info/METADATA
leanmq-0.2.0.dist-info/WHEEL
leanmq-0.2.0.dist-info/RECORD
