Metadata-Version: 2.3
Name: leanmq
Version: 0.2.0
Summary: Replace your internal webhooks with a reliable, performant, and scalable MQ with a fantastic DX.
License: Apache-2.0
Keywords: queue,message-queue,redis,microservices,streams
Author: Augustus D'Souza
Author-email: augustus.public@gmail.com
Requires-Python: >=3.11,<4.0
Classifier: Development Status :: 4 - Beta
Classifier: Intended Audience :: Developers
Classifier: License :: OSI Approved :: Apache Software License
Classifier: Programming Language :: Python :: 3
Classifier: Programming Language :: Python :: 3.11
Classifier: Topic :: Software Development :: Libraries
Classifier: Topic :: System :: Distributed Computing
Classifier: Topic :: System :: Networking
Requires-Dist: backoff (>=2.2.1)
Requires-Dist: redis (>=4.6.0)
Project-URL: Bug Tracker, https://github.com/augiwan/leanmq/issues
Project-URL: Documentation, https://github.com/augiwan/leanmq#readme
Project-URL: Homepage, https://github.com/augiwan/leanmq
